xlsxparse_joeypas/__init__.py
xlsxparse_joeypas/__main__.py
xlsxparse_joeypas/cli.py
xlsxparse_joeypas/parse.py
xlsxparse_joeypas/search.py
xlsxparse_joeypas-0.1.2.dist-info/METADATA
xlsxparse_joeypas-0.1.2.dist-info/WHEEL
xlsxparse_joeypas-0.1.2.dist-info/entry_points.txt
xlsxparse_joeypas-0.1.2.dist-info/licenses/LICENSE
xlsxparse_joeypas-0.1.2.dist-info/RECORD
