Metadata-Version: 2.4
Name: xlsxparse_joeypas
Version: 0.1.2
Summary: A .xlsx parser
Project-URL: Homepage, https://github.com/joeypas/xlsxparse
Project-URL: Issues, https://github.com/joeypas/xlsxparse/issues
Author-email: Joe Liotta <jliotta@uvm.edu>
License-Expression: MIT
License-File: LICENSE
Classifier: Operating System :: OS Independent
Classifier: Programming Language :: Python :: 3
Requires-Python: >=3.8
Requires-Dist: openpyxl
Requires-Dist: typer
